Metadata-Version: 2.1
Name: cppstart
Version: 0.1.1
Summary: Simplify the correct initialisation of C++ projects
Author-email: Kevin J Channon <kevinchannon+cppstart@gmail.com>
License: MIT
Project-URL: Documentation, https://github.com/kevinchannon/cppstart
Project-URL: Source, https://github.com/kevinchannon/cppstart
Keywords: C++,libraries
Classifier: Programming Language :: Python :: 3
Requires-Python: >=3.9
